bitcode/__init__.py
bitcode/bitcode.py
bitcode_test-1.0.0.dist-info/AUTHORS.rst
bitcode_test-1.0.0.dist-info/CHANGELOG.rst
bitcode_test-1.0.0.dist-info/CODE_OF_CONDUCT.rst
bitcode_test-1.0.0.dist-info/METADATA
bitcode_test-1.0.0.dist-info/NOTICE
bitcode_test-1.0.0.dist-info/WHEEL
bitcode_test-1.0.0.dist-info/apache-2.0.LICENSE
bitcode_test-1.0.0.dist-info/top_level.txt
bitcode_test-1.0.0.dist-info/RECORD
